Verilog_Practice/LedCircuit/design.v
module combinational_circuit(S,P,V,LED);

    input S,P,V;
    output LED;

    assign LED = (~S) & (P) & (V);

endmodule

Verilog_Practice/LedCircuit/testbench.v
module tb();
    reg S,P,V;
    wire LED;

    combinational_circuit dut(
        .S(S), .P(P), .V(V), .LED(LED)
    );

    initial begin
      $dumpfile("dump.vcd");
      $dumpvars(0);
    end

    initial begin
      S <= 1'b0;
      P <= 1'b0;
      V <= 1'b0;
      #100;
    
      S <= 1'b0;
      P <= 1'b0;
      V <= 1'b1;
      #100;

      S <= 1'b0;
      P <= 1'b1;
      V <= 1'b0;
      #100;

      S <= 1'b0;
      P <= 1'b1;
      V <= 1'b1;
      #100;

      S <= 1'b1;
      P <= 1'b0;
      V <= 1'b0;
      #100;

      S <= 1'b1;
      P <= 1'b0;
      V <= 1'b1;
      #100;

      S <= 1'b1;
      P <= 1'b1;
      V <= 1'b0;
      #100;

      S <= 1'b1;
      P <= 1'b1;
      V <= 1'b1;
      #100;
    end
    
endmodule

Verilog_Practice/LedCircuit/dump.vcd
$date
	Sat Nov 05 18:53:53 2022
$end
$version
	Icarus Verilog
$end
$timescale
	1s
$end
$scope module tb $end
$var wire 1 ! LED $end
$var reg 1 " P $end
$var reg 1 # S $end
$var reg 1 $ V $end
$scope module dut $end
$var wire 1 ! LED $end
$var wire 1 " P $end
$var wire 1 # S $end
$var wire 1 $ V $end
$upscope $end
$upscope $end
$enddefinitions $end
$comment Show the parameter values. $end
$dumpall
$end
#0
$dumpvars
0$
0#
0"
0!
$end
#100
1$
#200
0$
1"
#300
1!
1$
#400
0!
0$
0"
1#
#500
1$
#600
0$
1"
#700
1$
