LAB-01/combinational_circuit/design.v
module combinational_circuit(A, B, C, Q);

    //inputs
    input A, B, C;
    output Q;

    //interim signals
    wire A_xor_B;
    wire A_and_B;

    //logic designing
    assign A_xor_B = A ^ B;
    assign A_and_B = A & B;
    // final output
    assign Q = C | A_xor_B | A_and_B;

endmodule

// assign Q = (A ^ B) | (A & B) | C

LAB-01/combinational circuit/testbench.v
module tb();

    reg A, B, C;
    wire Q;

    // module declaration
    combinational_circuit dut (
        .A(A), .B(B), .C(C), .Q(Q)
    );

    initial begin
      A <= 1'b0;
      B <= 1'b0;
      C <= 1'b0;
      #100;

      A <= 1'b0;
      B <= 1'b0;
      C <= 1'b1;
      #100;

      A <= 1'b0;
      B <= 1'b1;
      C <= 1'b0;
      #100;

      A <= 1'b0;
      B <= 1'b1;
      C <= 1'b1;
      #100;

      A <= 1'b1;
      B <= 1'b0;
      C <= 1'b0;
      #100;

      A <= 1'b1;
      B <= 1'b0;
      C <= 1'b1;
      #100;
      A <= 1'b1;
      B <= 1'b1;
      C <= 1'b0;
      #100;

      A <= 1'b1;
      B <= 1'b1;
      C <= 1'b1;
      #100;
    end

    initial begin
      $dumpfile("dump.vcd");
      $dumpvars(0);
    end
        
endmodule

LAB-01/combinational circuit/dump.vcd
$date
	Sat Nov 05 13:57:12 2022
$end
$version
	Icarus Verilog
$end
$timescale
	1s
$end
$scope module tb $end
$var wire 1 ! Q $end
$var reg 1 " A $end
$var reg 1 # B $end
$var reg 1 $ C $end
$scope module dut $end
$var wire 1 " A $end
$var wire 1 % A_and_B $end
$var wire 1 & A_xor_B $end
$var wire 1 # B $end
$var wire 1 $ C $end
$var wire 1 ! Q $end
$upscope $end
$upscope $end
$enddefinitions $end
$comment Show the parameter values. $end
$dumpall
$end
#0
$dumpvars
0&
0%
0$
0#
0"
0!
$end
#100
1!
1$
#200
1&
0$
1#
#300
1$
#400
0$
0#
1"
#500
1$
#600
0&
1%
0$
1#
#700
1$
