LAB-01/3-bit counter/design.v
module two_bit_counter(input clk, reset,  output[2:0] Q);

    //input
    reg[2:0] flop;

    always @(posedge clk) begin
        if(reset == 1'b1) 
        begin
            flop <= 3'b000;
        end
        else begin
          flop <= flop + 3'b001;
        end
    end

    assign Q = flop;

endmodule

LAB-01/3-bit counter/testbench.v
module tb();

    reg clk, reset;
    wire[2:0] Q;

    // module declaration
    two_bit_counter dut (
        .clk(clk), .reset(reset), .Q(Q)
    );

    // clock cycle
    always begin
        clk <= 1'b0;
        #50;
        clk <= 1'b1;
        #50;
    end

    initial begin
      reset <= 1'b1;
      #100;
      reset <= 1'b0;
      #800;

      $finish;
    end

    initial begin
      $dumpfile("dump.vcd");
      $dumpvars(0);
    end
        
endmodule

LAB-01/3-bit counter/dump.vcd
$date
	Sat Nov 05 14:37:07 2022
$end
$version
	Icarus Verilog
$end
$timescale
	1s
$end
$scope module tb $end
$var wire 3 ! Q [2:0] $end
$var reg 1 " clk $end
$var reg 1 # reset $end
$scope module dut $end
$var wire 3 $ Q [2:0] $end
$var wire 1 " clk $end
$var wire 1 # reset $end
$var reg 3 % flop [2:0] $end
$upscope $end
$upscope $end
$enddefinitions $end
$comment Show the parameter values. $end
$dumpall
$end
#0
$dumpvars
bx %
bx $
1#
0"
bx !
$end
#50
b0 !
b0 $
b0 %
1"
#100
0"
0#
#150
b1 !
b1 $
b1 %
1"
#200
0"
#250
b10 !
b10 $
b10 %
1"
#300
0"
#350
b11 !
b11 $
b11 %
1"
#400
0"
#450
b100 !
b100 $
b100 %
1"
#500
0"
#550
b101 !
b101 $
b101 %
1"
#600
0"
#650
b110 !
b110 $
b110 %
1"
#700
0"
#750
b111 !
b111 $
b111 %
1"
#800
0"
#850
b0 !
b0 $
b0 %
1"
