Verilog_Practice/CompCombCir/design.v
module CompCombCir(A,B,C,Q);
    input A,B,C;
    output Q;

    wire A_nand_B, A_nor_B;

    assign A_nand_B = (~(A & B));
    assign A_nor_B = (~(A | B));
    assign Q = (A_nand_B) & (C) & (A_nor_B);

endmodule

Verilog_Practice/CompCombCir/testbench.v
module tb();
    reg A,B,C;
    wire Q;

    CompCombCir dut (
        .A(A), .B(B), .C(C), .Q(Q)
    );

    initial begin
      $dumpfile("dump.vcd");
      $dumpvars(0);
    end

    initial begin
      A <= 1'b0;
      B <= 1'b0;
      C <= 1'b0;
      #100;
    
      A <= 1'b0;
      B <= 1'b0;
      C <= 1'b1;
      #100;

      A <= 1'b0;
      B <= 1'b1;
      C <= 1'b0;
      #100;

      A <= 1'b0;
      B <= 1'b1;
      C <= 1'b1;
      #100;

      A <= 1'b1;
      B <= 1'b0;
      C <= 1'b0;
      #100;

      A <= 1'b1;
      B <= 1'b0;
      C <= 1'b1;
      #100;

      A <= 1'b1;
      B <= 1'b1;
      C <= 1'b0;
      #100;

      A <= 1'b1;
      B <= 1'b1;
      C <= 1'b1;
      #100;
    end

endmodule

Verilog_Practice/CompCombCir/dump.vcd
$date
	Sat Nov 05 19:04:54 2022
$end
$version
	Icarus Verilog
$end
$timescale
	1s
$end
$scope module tb $end
$var wire 1 ! Q $end
$var reg 1 " A $end
$var reg 1 # B $end
$var reg 1 $ C $end
$scope module dut $end
$var wire 1 " A $end
$var wire 1 % A_nand_B $end
$var wire 1 & A_nor_B $end
$var wire 1 # B $end
$var wire 1 $ C $end
$var wire 1 ! Q $end
$upscope $end
$upscope $end
$enddefinitions $end
$comment Show the parameter values. $end
$dumpall
$end
#0
$dumpvars
1&
1%
0$
0#
0"
0!
$end
#100
1!
1$
#200
0!
0&
0$
1#
#300
1$
#400
0$
0#
1"
#500
1$
#600
0%
0$
1#
#700
1$
