LAB-01/2-bit counter/design.v
module two_bit_counter(input clk, reset,  output[1:0] Q);

    //input
    reg[1:0] flop;

    always @(posedge clk) begin
        if(reset == 1'b1) 
        begin
            flop <= 2'b00;
        end
        else begin
          flop <= flop + 2'b01;
        end
    end

    assign Q = flop;

endmodule

LAB-01/2-bit counter/testbench.v
module tb();

    reg clk, reset;
    wire[1:0] Q;

    // module declaration
    two_bit_counter dut (
        .clk(clk), .reset(reset), .Q(Q)
    );

    // clock cycle
    always begin
        clk <= 1'b0;
        #50;
        clk <= 1'b1;
        #50;
    end

    initial begin
      reset <= 1'b1;
      
      #100;
      reset <= 1'b0;
      #500;

      $finish;
    end

    initial begin
      $dumpfile("dump.vcd");
      $dumpvars(0);
    end
        
endmodule

LAB-01/2-bit counter/dump.vcd
$date
	Sun Nov 06 01:18:51 2022
$end
$version
	Icarus Verilog
$end
$timescale
	1s
$end
$scope module tb $end
$var wire 2 ! Q [1:0] $end
$var reg 1 " clk $end
$var reg 1 # reset $end
$scope module dut $end
$var wire 2 $ Q [1:0] $end
$var wire 1 " clk $end
$var wire 1 # reset $end
$var reg 2 % flop [1:0] $end
$upscope $end
$upscope $end
$enddefinitions $end
$comment Show the parameter values. $end
$dumpall
$end
#0
$dumpvars
bx %
bx $
1#
0"
bx !
$end
#50
b0 !
b0 $
b0 %
1"
#100
0"
0#
#150
b1 !
b1 $
b1 %
1"
#200
0"
#250
b10 !
b10 $
b10 %
1"
#300
0"
#350
b11 !
b11 $
b11 %
1"
#400
0"
#450
b0 !
b0 $
b0 %
1"
#500
0"
#550
b1 !
b1 $
b1 %
1"
