LAB-01/post-lab-task/design.v
module combinational_circuit(A, B, C, D, Z);
    // inputs
    input A, B, C, D;

    // interim wires
    wire B_xor_D;
    wire B_and_C;
    wire C_or_D;
    wire not_C_or_D;
    wire A_or_not_C_or_D;
    wire B_xor_D_or_B_and_C;

    // output
    output Z;

    // assignment with logical operations
    assign B_xor_D = B ^ D;
    assign B_and_C = B & C;
    assign C_or_D = C | D;
    assign not_C_or_D = !(C_or_D);
    assign A_or_not_C_or_D = A | not_C_or_D;
    assign B_xor_D_or_B_and_C = B_xor_D | B_and_C;
    // final output 
    assign Z = A_or_not_C_or_D ^ B_xor_D_or_B_and_C;

endmodule

// assign Z = (A | (!(C | D))) ^ ((B ^ D) | (B & C));
// assign Z = (!(A) & !(B) & D) + (!(A) & B & C); // !A.!B.D + !A.B.C

LAB-01/post-lab-task/testbench.v
module tb();
    reg A, B, C, D;
    wire Z;

    // module declaration
    combinational_circuit dut (
        .A(A), .B(B), .C(C), .D(D), .Z(Z)
    );

    initial begin
      A <= 1'b0;
      B <= 1'b0;
      C <= 1'b0;
      D <= 1'b0;
      #100;

      A <= 1'b0;
      B <= 1'b0;
      C <= 1'b0;
      D <= 1'b1;
      #100;
      
      A <= 1'b0;
      B <= 1'b0;
      C <= 1'b1;
      D <= 1'b0;
      #100;
      
      A <= 1'b0;
      B <= 1'b0;
      C <= 1'b1;
      D <= 1'b1;
      #100;

      A <= 1'b0;
      B <= 1'b1;
      C <= 1'b0;
      D <= 1'b0;
      #100;
      
      A <= 1'b0;
      B <= 1'b1;
      C <= 1'b0;
      D <= 1'b1;
      #100;
      
      A <= 1'b0;
      B <= 1'b1;
      C <= 1'b1;
      D <= 1'b0;
      #100;
      A <= 1'b0;
      B <= 1'b1;
      C <= 1'b1;
      D <= 1'b1;
      #100;

      A <= 1'b1;
      B <= 1'b0;
      C <= 1'b0;
      D <= 1'b0;
      #100;
      
      A <= 1'b1;
      B <= 1'b0;
      C <= 1'b0;
      D <= 1'b1;
      #100;
      
      A <= 1'b1;
      B <= 1'b0;
      C <= 1'b1;
      D <= 1'b0;
      #100;
      A <= 1'b1;
      B <= 1'b0;
      C <= 1'b1;
      D <= 1'b1;
      #100;

      A <= 1'b1;
      B <= 1'b1;
      C <= 1'b0;
      D <= 1'b0;
      #100;
      
      A <= 1'b1;
      B <= 1'b1;
      C <= 1'b0;
      D <= 1'b1;
      #100;
      
      A <= 1'b1;
      B <= 1'b1;
      C <= 1'b1;
      D <= 1'b0;
      #100;

      A <= 1'b1;
      B <= 1'b1;
      C <= 1'b1;
      D <= 1'b1;
      #100;
    
    end

    initial begin
      $dumpfile("dump.vcd");
      $dumpvars(0);
    end
    
endmodule

LAB-01/post-lab-task/dump.vcd
$date
	Sat Nov 05 03:11:41 2022
$end
$version
	Icarus Verilog
$end
$timescale
	1s
$end
$scope module tb $end
$var wire 1 ! Z $end
$var reg 1 " A $end
$var reg 1 # B $end
$var reg 1 $ C $end
$var reg 1 % D $end
$scope module dut $end
$var wire 1 " A $end
$var wire 1 & A_or_not_C_or_D $end
$var wire 1 # B $end
$var wire 1 ' B_and_C $end
$var wire 1 ( B_xor_D $end
$var wire 1 ) B_xor_D_or_B_and_C $end
$var wire 1 $ C $end
$var wire 1 * C_or_D $end
$var wire 1 % D $end
$var wire 1 ! Z $end
$var wire 1 + not_C_or_D $end
$upscope $end
$upscope $end
$enddefinitions $end
$comment Show the parameter values. $end
$dumpall
$end
#0
$dumpvars
1+
0*
0)
0(
0'
1&
0%
0$
0#
0"
1!
$end
#100
1)
0&
1(
0+
1*
1%
#200
0!
0)
0(
0%
1$
#300
1!
1)
1(
1%
#400
0!
1&
1+
0*
0%
0$
1#
#500
0)
0&
0(
0+
1*
1%
#600
1!
1)
1(
1'
0%
1$
#700
0(
1%
#800
0)
1!
1+
0*
0'
1&
0%
0$
0#
1"
#900
0!
1)
1(
0+
1*
1%
#1000
1!
0)
0(
0%
1$
#1100
0!
1)
1(
1%
#1200
1+
0*
0%
0$
1#
#1300
1!
0)
0(
0+
1*
1%
#1400
0!
1)
1(
1'
0%
1$
#1500
0(
1%
